pyflights/__init__.py
pyflights/pyflight.py
pyflights/objects/__init__.py
pyflights/objects/flight.py
pyflights-0.3.1.dist-info/DESCRIPTION.rst
pyflights-0.3.1.dist-info/METADATA
pyflights-0.3.1.dist-info/RECORD
pyflights-0.3.1.dist-info/WHEEL
pyflights-0.3.1.dist-info/metadata.json
pyflights-0.3.1.dist-info/top_level.txt
