Metadata-Version: 2.0
Name: pyflights
Version: 0.3.1
Summary: A wrapper for the Google Flights Search API.
Home-page: https://github.com/AnthonyBloomer/pyflights
Author: Anthony Bloomer
Author-email: ant0@protonmail.ch
License: MIT
Keywords: Google Flights,Flights,API,QPX Express Airfare API
Platform: UNKNOWN
Classifier: Intended Audience :: Developers
Classifier: License :: OSI Approved :: MIT License
Classifier: Topic :: Software Development :: Libraries
Classifier: Programming Language :: Python
Classifier: Programming Language :: Python :: 2.7
Classifier: Programming Language :: Python :: 3
Classifier: Programming Language :: Python :: 3.3
Classifier: Programming Language :: Python :: 3.4
Classifier: Programming Language :: Python :: 3.5
Classifier: Programming Language :: Python :: 3.6
Requires-Dist: requests
